pycryptcli/__init__.py
pycryptcli/__main__.py
pycryptcli/techniques.py
pycrypt_cli-0.5.dist-info/LICENSE.txt
pycrypt_cli-0.5.dist-info/METADATA
pycrypt_cli-0.5.dist-info/WHEEL
pycrypt_cli-0.5.dist-info/entry_points.txt
pycrypt_cli-0.5.dist-info/top_level.txt
pycrypt_cli-0.5.dist-info/RECORD
