Metadata-Version: 2.1
Name: pycrypt-cli
Version: 0.5
Summary: Cryption tool
Home-page: https://github.com/Devansh3712/pycrypt-cli
Author: Devansh Singh
Author-email: devanshamity@gmail.com
License: MIT
Platform: UNKNOWN
Classifier: Programming Language :: Python :: 3
Classifier: License :: OSI Approved :: MIT License
Classifier: Operating System :: OS Independent
Requires-Dist: click (==7.1.2)
